azure/mgmt/eventhub/__init__.py
azure/mgmt/eventhub/_configuration.py
azure/mgmt/eventhub/_event_hub_management_client.py
azure/mgmt/eventhub/_serialization.py
azure/mgmt/eventhub/_version.py
azure/mgmt/eventhub/models.py
azure/mgmt/eventhub/py.typed
azure/mgmt/eventhub/aio/__init__.py
azure/mgmt/eventhub/aio/_configuration.py
azure/mgmt/eventhub/aio/_event_hub_management_client.py
azure/mgmt/eventhub/v2015_08_01/__init__.py
azure/mgmt/eventhub/v2015_08_01/_configuration.py
azure/mgmt/eventhub/v2015_08_01/_event_hub_management_client.py
azure/mgmt/eventhub/v2015_08_01/_patch.py
azure/mgmt/eventhub/v2015_08_01/_version.py
azure/mgmt/eventhub/v2015_08_01/py.typed
azure/mgmt/eventhub/v2015_08_01/aio/__init__.py
azure/mgmt/eventhub/v2015_08_01/aio/_configuration.py
azure/mgmt/eventhub/v2015_08_01/aio/_event_hub_management_client.py
azure/mgmt/eventhub/v2015_08_01/aio/_patch.py
azure/mgmt/eventhub/v2015_08_01/aio/operations/__init__.py
azure/mgmt/eventhub/v2015_08_01/aio/operations/_consumer_groups_operations.py
azure/mgmt/eventhub/v2015_08_01/aio/operations/_event_hubs_operations.py
azure/mgmt/eventhub/v2015_08_01/aio/operations/_namespaces_operations.py
azure/mgmt/eventhub/v2015_08_01/aio/operations/_operations.py
azure/mgmt/eventhub/v2015_08_01/aio/operations/_patch.py
azure/mgmt/eventhub/v2015_08_01/models/__init__.py
azure/mgmt/eventhub/v2015_08_01/models/_event_hub_management_client_enums.py
azure/mgmt/eventhub/v2015_08_01/models/_models_py3.py
azure/mgmt/eventhub/v2015_08_01/models/_patch.py
azure/mgmt/eventhub/v2015_08_01/operations/__init__.py
azure/mgmt/eventhub/v2015_08_01/operations/_consumer_groups_operations.py
azure/mgmt/eventhub/v2015_08_01/operations/_event_hubs_operations.py
azure/mgmt/eventhub/v2015_08_01/operations/_namespaces_operations.py
azure/mgmt/eventhub/v2015_08_01/operations/_operations.py
azure/mgmt/eventhub/v2015_08_01/operations/_patch.py
azure/mgmt/eventhub/v2017_04_01/__init__.py
azure/mgmt/eventhub/v2017_04_01/_configuration.py
azure_mgmt_eventhub-11.2.0.dist-info/LICENSE
azure_mgmt_eventhub-11.2.0.dist-info/METADATA
azure_mgmt_eventhub-11.2.0.dist-info/WHEEL
azure_mgmt_eventhub-11.2.0.dist-info/top_level.txt
azure_mgmt_eventhub-11.2.0.dist-info/RECORD
